deployer/__init__.py
deployer/_templates/components/dummy_component.py
deployer/_templates/configs/config.json
deployer/_templates/configs/config.py
deployer/_templates/configs/config.toml
deployer/_templates/configs/config.yaml
deployer/_templates/deployer.env
deployer/_templates/deployment/Dockerfile
deployer/_templates/deployment/build_base_image.sh.jinja
deployer/_templates/deployment/cloudbuild_local.yaml.jinja
deployer/_templates/pipelines/pipeline_minimal.py.jinja
deployer/_templates/requirements-vertex.txt.jinja
deployer/cli.py
deployer/constants.py
deployer/init_deployer.py
deployer/pipeline_checks.py
deployer/pipeline_deployer.py
deployer/settings.py
deployer/utils/config.py
deployer/utils/console.py
deployer/utils/exceptions.py
deployer/utils/logging.py
deployer/utils/models.py
deployer/utils/utils.py
vertex_deployer-0.5.5.dist-info/LICENSE
vertex_deployer-0.5.5.dist-info/METADATA
vertex_deployer-0.5.5.dist-info/WHEEL
vertex_deployer-0.5.5.dist-info/entry_points.txt
vertex_deployer-0.5.5.dist-info/RECORD
