Metadata-Version: 2.3
Name: vertex-deployer
Version: 0.5.5
Summary: Check, compile, upload, run, and schedule Kubeflow Pipelines on GCP Vertex AI in a standardized manner.
License: Apache-2.0
Keywords: kubeflow,vertexai,aiplatform,gcp,mlops,deployer,pipeline
Author: artefactory
Author-email: jules.bertrand@artefact.com
Requires-Python: >=3.8,<3.13.0
Classifier: License :: OSI Approved :: Apache Software License
Classifier: Programming Language :: Python :: 3
Classifier: Programming Language :: Python :: 3.8
Classifier: Programming Language :: Python :: 3.9
Classifier: Programming Language :: Python :: 3.10
Classifier: Programming Language :: Python :: 3.11
Classifier: Programming Language :: Python :: 3.12
Provides-Extra: profiling
Requires-Dist: google-cloud-aiplatform (>=1.26,<2.0)
Requires-Dist: jinja2 (>=3.1.3,<4.0.0)
Requires-Dist: kfp (>=2.0.1,<3.0)
Requires-Dist: loguru (>=0.7,<0.8)
Requires-Dist: numpy (<1.25) ; python_version < "3.9"
Requires-Dist: numpy (>1.24) ; python_version >= "3.9"
Requires-Dist: pydantic (>=2.3,<3.0)
Requires-Dist: pydantic-settings (>=2.0,<2.9.0)
Requires-Dist: pyinstrument (>=4.5,<6.0) ; extra == "profiling"
Requires-Dist: requests (>=2.31,<3.0)
Requires-Dist: rich (>=13.5,<14.0)
Requires-Dist: toml (>=0.10,<0.11)
Requires-Dist: tomlkit (>=0.12,<0.14)
Requires-Dist: typer (>=0.12,<0.13)
Project-URL: Documentation, https://artefactory.github.io/vertex-pipelines-deployer/
Project-URL: Homepage, https://github.com/artefactory/vertex-pipelines-deployer
Project-URL: Repository, https://github.com/artefactory/vertex-pipelines-deployer
